<annotation>
	<folder>pluma</folder>
	<filename>pluma.24235a2e-3abb-11ec-8fab-fcb3bc942209.jpg</filename>
	<path>C:\Users\jonat\PycharmProjects\CriminalDetectionML\Tensorflow\workspace\images\collectedimages\pluma\pluma.24235a2e-3abb-11ec-8fab-fcb3bc942209.jpg</path>
	<source>
		<database>Unknown</database>
	</source>
	<size>
		<width>640</width>
		<height>480</height>
		<depth>3</depth>
	</size>
	<segmented>0</segmented>
	<object>
		<name>pluma</name>
		<pose>Unspecified</pose>
		<truncated>0</truncated>
		<difficult>0</difficult>
		<bndbox>
			<xmin>109</xmin>
			<ymin>134</ymin>
			<xmax>219</xmax>
			<ymax>250</ymax>
		</bndbox>
	</object>
	<object>
		<name>pluma</name>
		<pose>Unspecified</pose>
		<truncated>0</truncated>
		<difficult>0</difficult>
		<bndbox>
			<xmin>382</xmin>
			<ymin>265</ymin>
			<xmax>520</xmax>
			<ymax>344</ymax>
		</bndbox>
	</object>
</annotation>
