<annotation>
	<folder>pluma</folder>
	<filename>pluma.0f449afd-3abb-11ec-abd3-fcb3bc942209.jpg</filename>
	<path>C:\Users\jonat\PycharmProjects\CriminalDetectionML\Tensorflow\workspace\images\collectedimages\pluma\pluma.0f449afd-3abb-11ec-abd3-fcb3bc942209.jpg</path>
	<source>
		<database>Unknown</database>
	</source>
	<size>
		<width>640</width>
		<height>480</height>
		<depth>3</depth>
	</size>
	<segmented>0</segmented>
	<object>
		<name>pluma</name>
		<pose>Unspecified</pose>
		<truncated>0</truncated>
		<difficult>0</difficult>
		<bndbox>
			<xmin>160</xmin>
			<ymin>133</ymin>
			<xmax>306</xmax>
			<ymax>160</ymax>
		</bndbox>
	</object>
	<object>
		<name>pluma</name>
		<pose>Unspecified</pose>
		<truncated>0</truncated>
		<difficult>0</difficult>
		<bndbox>
			<xmin>374</xmin>
			<ymin>183</ymin>
			<xmax>527</xmax>
			<ymax>241</ymax>
		</bndbox>
	</object>
</annotation>
